{
  "leaderboard": [
    {
      "strategy_name": "mom-lb24-top1-gross0.5",
      "params": {
        "name": "mom-lb24-top1-gross0.5",
        "lookback_bars": 24,
        "top_k": 1,
        "gross_target": 0.5
      },
      "accepted": false,
      "score": -94.89634487103203,
      "metrics": {
        "total_return": -0.19102485485623644,
        "sharpe": -92.95408968247119,
        "max_drawdown": 0.1945494779495689,
        "average_turnover": 0.20893300248138957,
        "bars_processed": 2015
      },
      "rejection_reasons": [
        "total_return_below_gate",
        "sharpe_below_gate"
      ]
    },
    {
      "strategy_name": "mom-lb24-top1-gross1.0",
      "params": {
        "name": "mom-lb24-top1-gross1.0",
        "lookback_bars": 24,
        "top_k": 1,
        "gross_target": 1.0
      },
      "accepted": false,
      "score": -94.89634487103203,
      "metrics": {
        "total_return": -0.19102485485623644,
        "sharpe": -92.95408968247119,
        "max_drawdown": 0.1945494779495689,
        "average_turnover": 0.20893300248138957,
        "bars_processed": 2015
      },
      "rejection_reasons": [
        "total_return_below_gate",
        "sharpe_below_gate"
      ]
    },
    {
      "strategy_name": "mom-lb24-top2-gross0.5",
      "params": {
        "name": "mom-lb24-top2-gross0.5",
        "lookback_bars": 24,
        "top_k": 2,
        "gross_target": 0.5
      },
      "accepted": false,
      "score": -104.28890691610476,
      "metrics": {
        "total_return": -0.14418605858880829,
        "sharpe": -102.83736011131093,
        "max_drawdown": 0.14623973590289563,
        "average_turnover": 0.1456575682382134,
        "bars_processed": 2015
      },
      "rejection_reasons": [
        "total_return_below_gate",
        "sharpe_below_gate"
      ]
    },
    {
      "strategy_name": "mom-lb12-top2-gross0.5",
      "params": {
        "name": "mom-lb12-top2-gross0.5",
        "lookback_bars": 12,
        "top_k": 2,
        "gross_target": 0.5
      },
      "accepted": false,
      "score": -114.46447006015492,
      "metrics": {
        "total_return": -0.16376357308792944,
        "sharpe": -112.79934557704576,
        "max_drawdown": 0.16418211347445433,
        "average_turnover": 0.18957816377171216,
        "bars_processed": 2015
      },
      "rejection_reasons": [
        "total_return_below_gate",
        "sharpe_below_gate"
      ]
    },
    {
      "strategy_name": "baseline",
      "params": {
        "name": "baseline",
        "lookback_bars": 12,
        "top_k": 2,
        "gross_target": 1.0
      },
      "accepted": false,
      "score": -115.16122071773378,
      "metrics": {
        "total_return": -0.2924624662072326,
        "sharpe": -112.15701325853381,
        "max_drawdown": 0.293170389495626,
        "average_turnover": 0.3692135701813121,
        "bars_processed": 2015
      },
      "rejection_reasons": [
        "total_return_below_gate",
        "sharpe_below_gate"
      ]
    }
  ]
}