{
  "leaderboard": [
    {
      "strategy_name": "mom-lb24-top1-gross0.5",
      "params": {
        "name": "mom-lb24-top1-gross0.5",
        "lookback_bars": 24,
        "top_k": 1,
        "gross_target": 0.5
      },
      "accepted": false,
      "score": -115.44296426935867,
      "metrics": {
        "total_return": -0.20775110167016964,
        "sharpe": -113.35716474357592,
        "max_drawdown": 0.20859723264581576,
        "average_turnover": 0.21265508684863524,
        "bars_processed": 2015
      },
      "rejection_reasons": [
        "total_return_below_gate",
        "sharpe_below_gate"
      ]
    },
    {
      "strategy_name": "mom-lb24-top1-gross1.0",
      "params": {
        "name": "mom-lb24-top1-gross1.0",
        "lookback_bars": 24,
        "top_k": 1,
        "gross_target": 1.0
      },
      "accepted": false,
      "score": -115.44296426935867,
      "metrics": {
        "total_return": -0.20775110167016964,
        "sharpe": -113.35716474357592,
        "max_drawdown": 0.20859723264581576,
        "average_turnover": 0.21265508684863524,
        "bars_processed": 2015
      },
      "rejection_reasons": [
        "total_return_below_gate",
        "sharpe_below_gate"
      ]
    },
    {
      "strategy_name": "mom-lb24-top2-gross0.5",
      "params": {
        "name": "mom-lb24-top2-gross0.5",
        "lookback_bars": 24,
        "top_k": 2,
        "gross_target": 0.5
      },
      "accepted": false,
      "score": -118.52959071949327,
      "metrics": {
        "total_return": -0.1492139007226818,
        "sharpe": -117.04623690610512,
        "max_drawdown": 0.14924043228239414,
        "average_turnover": 0.1403225806451613,
        "bars_processed": 2015
      },
      "rejection_reasons": [
        "total_return_below_gate",
        "sharpe_below_gate"
      ]
    },
    {
      "strategy_name": "mom-lb12-top2-gross0.5",
      "params": {
        "name": "mom-lb12-top2-gross0.5",
        "lookback_bars": 12,
        "top_k": 2,
        "gross_target": 0.5
      },
      "accepted": false,
      "score": -133.8664299521754,
      "metrics": {
        "total_return": -0.17311293273328376,
        "sharpe": -132.12106864442447,
        "max_drawdown": 0.17311293273328376,
        "average_turnover": 0.18734491315136476,
        "bars_processed": 2015
      },
      "rejection_reasons": [
        "total_return_below_gate",
        "sharpe_below_gate"
      ]
    },
    {
      "strategy_name": "baseline",
      "params": {
        "name": "baseline",
        "lookback_bars": 12,
        "top_k": 2,
        "gross_target": 1.0
      },
      "accepted": false,
      "score": -135.36437504093604,
      "metrics": {
        "total_return": -0.3067652749899257,
        "sharpe": -132.23916404009026,
        "max_drawdown": 0.3067652749899257,
        "average_turnover": 0.36432352593642914,
        "bars_processed": 2015
      },
      "rejection_reasons": [
        "total_return_below_gate",
        "sharpe_below_gate"
      ]
    }
  ]
}