{
  "leaderboard": [
    {
      "strategy_name": "mom-lb24-top1-gross0.5",
      "params": {
        "name": "mom-lb24-top1-gross0.5",
        "lookback_bars": 24,
        "top_k": 1,
        "gross_target": 0.5
      },
      "accepted": false,
      "score": -107.9780108553347,
      "metrics": {
        "total_return": -0.20481242922074394,
        "sharpe": -105.90008990961903,
        "max_drawdown": 0.2096185460568344,
        "average_turnover": 0.2153846153846154,
        "bars_processed": 2015
      },
      "rejection_reasons": [
        "total_return_below_gate",
        "sharpe_below_gate"
      ]
    },
    {
      "strategy_name": "mom-lb24-top1-gross1.0",
      "params": {
        "name": "mom-lb24-top1-gross1.0",
        "lookback_bars": 24,
        "top_k": 1,
        "gross_target": 1.0
      },
      "accepted": false,
      "score": -107.9780108553347,
      "metrics": {
        "total_return": -0.20481242922074394,
        "sharpe": -105.90008990961903,
        "max_drawdown": 0.2096185460568344,
        "average_turnover": 0.2153846153846154,
        "bars_processed": 2015
      },
      "rejection_reasons": [
        "total_return_below_gate",
        "sharpe_below_gate"
      ]
    },
    {
      "strategy_name": "mom-lb24-top2-gross0.5",
      "params": {
        "name": "mom-lb24-top2-gross0.5",
        "lookback_bars": 24,
        "top_k": 2,
        "gross_target": 0.5
      },
      "accepted": false,
      "score": -112.37011832733656,
      "metrics": {
        "total_return": -0.1496167735558045,
        "sharpe": -110.87122411201445,
        "max_drawdown": 0.15141226430512778,
        "average_turnover": 0.14516129032258066,
        "bars_processed": 2015
      },
      "rejection_reasons": [
        "total_return_below_gate",
        "sharpe_below_gate"
      ]
    },
    {
      "strategy_name": "mom-lb12-top2-gross0.5",
      "params": {
        "name": "mom-lb12-top2-gross0.5",
        "lookback_bars": 12,
        "top_k": 2,
        "gross_target": 0.5
      },
      "accepted": false,
      "score": -125.57719893318487,
      "metrics": {
        "total_return": -0.1713761543760146,
        "sharpe": -123.84286113326566,
        "max_drawdown": 0.17153547289067772,
        "average_turnover": 0.1913151364764268,
        "bars_processed": 2015
      },
      "rejection_reasons": [
        "total_return_below_gate",
        "sharpe_below_gate"
      ]
    },
    {
      "strategy_name": "baseline",
      "params": {
        "name": "baseline",
        "lookback_bars": 12,
        "top_k": 2,
        "gross_target": 1.0
      },
      "accepted": false,
      "score": -126.3779551215592,
      "metrics": {
        "total_return": -0.3038674112702253,
        "sharpe": -123.2698872471384,
        "max_drawdown": 0.30413489509863667,
        "average_turnover": 0.37219123767510864,
        "bars_processed": 2015
      },
      "rejection_reasons": [
        "total_return_below_gate",
        "sharpe_below_gate"
      ]
    }
  ]
}